easyphysics/__init__.py
easyphysics/freefall.py
easyphysics/gravitational_energy.py
easyphysics/kinetic_energy.py
easyphysics/static_friction.py
easyphysics-0.1.0.dist-info/LICENSE
easyphysics-0.1.0.dist-info/METADATA
easyphysics-0.1.0.dist-info/WHEEL
easyphysics-0.1.0.dist-info/RECORD
