Metadata-Version: 2.1
Name: easyphysics
Version: 0.1.0
Summary: A package with useful physics formulas to make physics easy and fun for users!
License: MIT
Author: Group 16
Requires-Python: >=3.9,<4.0
Classifier: License :: OSI Approved :: MIT License
Classifier: Programming Language :: Python :: 3
Classifier: Programming Language :: Python :: 3.9
Classifier: Programming Language :: Python :: 3.10
Classifier: Programming Language :: Python :: 3.11
Requires-Dist: altair (>=4.2.0,<5.0.0)
Requires-Dist: matplotlib (>=3.6.3,<4.0.0)
